snstorch/__init__.py
snstorch/modules.py
snstorch-0.1.3.dist-info/LICENSE
snstorch-0.1.3.dist-info/METADATA
snstorch-0.1.3.dist-info/WHEEL
snstorch-0.1.3.dist-info/top_level.txt
snstorch-0.1.3.dist-info/RECORD
